Metadata-Version: 1.0
Name: arpyes
Version: 0.1
Summary: Analysis package for Diamond Light Source ARPES data.
Home-page: http://github.com/domherriott/arpyes
Author: Dominic Herriott
Author-email: herriott95@gmail.com
License: MIT
Platform: UNKNOWN
